{"cameraMode":{"drawMode":0,"name":"Shaded","section":"Shading Mode"},"sceneLighting":true,"audioPlay":false,"sceneViewState":{"showFog":true,"showMaterialUpdate":false,"showSkybox":true,"showFlares":true,"showImageEffects":true,"showParticleSystems":true},"in2DMode":false,"pivot":{"x":233.99301147460938,"y":125.46873474121094,"z":1.63616943359375},"rotation":{"x":-0.020574472844600679,"y":-0.9772282242774963,"z":0.17873647809028626,"w":-0.11249423772096634},"size":424.7947998046875,"orthographic":false}